web_crawling/__init__.py
web_crawling/code.py
web_crawling-0.0.1.dist-info/METADATA
web_crawling-0.0.1.dist-info/WHEEL
web_crawling-0.0.1.dist-info/top_level.txt
web_crawling-0.0.1.dist-info/RECORD
