Metadata-Version: 2.1
Name: web-crawling
Version: 0.0.1
Summary: generate climate forecasts using place
Home-page: https://github.com/Deepsikha97/WeatherWebCrawling
Author: Deepsikha Roy
Author-email: iamdeepsikha2012@gmail.com
License: UNKNOWN
Platform: UNKNOWN
Classifier: Programming Language :: Python :: 3
Classifier: Operating System :: OS Independent
Requires-Python: >=3.6
